easyjobs/__init__.py
easyjobs/manager.py
easyjobs/api/__init__.py
easyjobs/api/manager_api.py
easyjobs/brokers/__init__.py
easyjobs/brokers/easyjobs.py
easyjobs/brokers/rabbitmq.py
easyjobs/producers/__init__.py
easyjobs/producers/rabbitmq.py
easyjobs/workers/__init__.py
easyjobs/workers/task.py
easyjobs/workers/task_subprocess.py
easyjobs/workers/worker.py
easyjobs-0.127.dist-info/LICENSE.md
easyjobs-0.127.dist-info/METADATA
easyjobs-0.127.dist-info/WHEEL
easyjobs-0.127.dist-info/top_level.txt
easyjobs-0.127.dist-info/RECORD
