Metadata-Version: 2.1
Name: easyjobs
Version: 0.127
Summary: An easy to use, celerly-like jobs framework, for creating, distributing, and managing workloads
Home-page: https://github.com/codemation/easyjobs
Author: Joshua Jamison
Author-email: joshjamison1@gmail.com
License: UNKNOWN
Platform: UNKNOWN
Classifier: Programming Language :: Python :: 3
Classifier: License :: OSI Approved :: MIT License
Classifier: Operating System :: OS Independent
Requires-Python: >=3.7, <4
Requires-Dist: easyrpc (>=0.239)
Requires-Dist: aiopyql (>=0.355)
Requires-Dist: easyschedule (>=0.104)
